README.md
setup.py
Package_robot/Map.py
Package_robot/__init__.py
TP2_Robot_EBERMEYER_Tom.egg-info/PKG-INFO
TP2_Robot_EBERMEYER_Tom.egg-info/SOURCES.txt
TP2_Robot_EBERMEYER_Tom.egg-info/dependency_links.txt
TP2_Robot_EBERMEYER_Tom.egg-info/top_level.txt