Metadata-Version: 1.1
Name: TP2-Robot-EBERMEYER-Tom
Version: 0.0.1
Summary: Deplacement d'un robot (modélisé par un '1') dans un grille de '0' de taille définie par l'user.
Home-page: UNKNOWN
Author: Tom Ebermeyer
Author-email: tom.ebermeyer@cpe.fr
License: UNKNOWN
Platform: UNKNOWN
Classifier: Programming Language :: Python :: 3
Classifier: Operating System :: OS Independent
